odoo10_addon_web_ir_actions_act_window_page-10.0.1.0.0.99.dev3-py2.7-nspkg.pth
odoo/addons/web_ir_actions_act_window_page/README.md
odoo/addons/web_ir_actions_act_window_page/__init__.py
odoo/addons/web_ir_actions_act_window_page/__manifest__.py
odoo/addons/web_ir_actions_act_window_page/demo/demo_action.xml
odoo/addons/web_ir_actions_act_window_page/i18n/de.po
odoo/addons/web_ir_actions_act_window_page/i18n/web_ir_actions_act_window_page.pot
odoo/addons/web_ir_actions_act_window_page/static/description/icon.png
odoo/addons/web_ir_actions_act_window_page/static/src/js/web_ir_actions_act_window_page.js
odoo/addons/web_ir_actions_act_window_page/views/assets.xml
odoo10_addon_web_ir_actions_act_window_page-10.0.1.0.0.99.dev3.dist-info/DESCRIPTION.rst
odoo10_addon_web_ir_actions_act_window_page-10.0.1.0.0.99.dev3.dist-info/METADATA
odoo10_addon_web_ir_actions_act_window_page-10.0.1.0.0.99.dev3.dist-info/RECORD
odoo10_addon_web_ir_actions_act_window_page-10.0.1.0.0.99.dev3.dist-info/WHEEL
odoo10_addon_web_ir_actions_act_window_page-10.0.1.0.0.99.dev3.dist-info/metadata.json
odoo10_addon_web_ir_actions_act_window_page-10.0.1.0.0.99.dev3.dist-info/namespace_packages.txt
odoo10_addon_web_ir_actions_act_window_page-10.0.1.0.0.99.dev3.dist-info/top_level.txt
